pytrafficflow/__init__.py
pytrafficflow/core/base_model.py
pytrafficflow/core/vehicle.py
pytrafficflow/core/velocity.py
pytrafficflow/data/loader.py
pytrafficflow/data/preprocess.py
pytrafficflow/data/synthetic/one_road.py
pytrafficflow/models/particle.py
pytrafficflow/tests/lwr_tests.py
pytrafficflow/utils/visualization.py
pytrafficflow-1.0.0.dist-info/licenses/LICENSE
pytrafficflow-1.0.0.dist-info/METADATA
pytrafficflow-1.0.0.dist-info/WHEEL
pytrafficflow-1.0.0.dist-info/entry_points.txt
pytrafficflow-1.0.0.dist-info/top_level.txt
pytrafficflow-1.0.0.dist-info/RECORD
